pretalx_zammad/__init__.py
pretalx_zammad/apps.py
pretalx_zammad/forms.py
pretalx_zammad/models.py
pretalx_zammad/signals.py
pretalx_zammad/urls.py
pretalx_zammad/views.py
pretalx_zammad/locale/de_DE/LC_MESSAGES/django.po
pretalx_zammad/locale/de_Formal/LC_MESSAGES/django.po
pretalx_zammad/migrations/__init__.py
pretalx_zammad/static/pretalx_zammad/.gitkeep
pretalx_zammad/static/pretalx_zammad/logo.svg
pretalx_zammad/templates/pretalx_zammad/form.html
pretalx_zammad/templates/pretalx_zammad/samaware.html
pretalx_zammad/templates/pretalx_zammad/settings.html
pretalx_zammad-2025.0.1.dist-info/licenses/LICENSE
pretalx_zammad-2025.0.1.dist-info/METADATA
pretalx_zammad-2025.0.1.dist-info/WHEEL
pretalx_zammad-2025.0.1.dist-info/entry_points.txt
pretalx_zammad-2025.0.1.dist-info/top_level.txt
pretalx_zammad-2025.0.1.dist-info/RECORD
