Metadata-Version: 2.4
Name: pretalx-zammad
Version: 2025.0.1
Summary: pretalx plugin for Zammad issue tracker
Author-email: Florian Moesch <florian@moesch.org>
Maintainer-email: Florian Moesch <florian@moesch.org>
License: Apache Software License
Project-URL: homepage, https://github.com/badbadc0ffee/pretalx-zammad
Project-URL: repository, https://github.com/badbadc0ffee/pretalx-zammad.git
Keywords: pretalx
License-File: LICENSE
Requires-Dist: zammad-py
Provides-Extra: dev
Requires-Dist: black; extra == "dev"
Requires-Dist: build; extra == "dev"
Requires-Dist: check-manifest; extra == "dev"
Requires-Dist: flake8; extra == "dev"
Requires-Dist: isort; extra == "dev"
Dynamic: license-file
